{
  "symbol": "KO",
  "date_t": "2025-12-11",
  "method": "GBM-CC",
  "y_hat": 69.11000061035156,
  "params": {
    "window": 504,
    "lambda_drift": 0,
    "coverage": 0.95,
    "h": 1
  },
  "estimates": {
    "mu_star_hat": 0.0004399591059269381,
    "sigma_hat": 0.009644266804269268,
    "mu_star_used": 0,
    "window_start": "2023-12-07",
    "window_end": "2025-12-11",
    "n": 504
  },
  "target": {
    "h": 1,
    "coverage": 0.95
  },
  "S_t": 69.11000061035156,
  "critical": {
    "type": "normal",
    "z_alpha": 1.959963986120195
  },
  "m_log": 4.235699446934898,
  "s_scale": 0.009644266804269268,
  "L_h": 67.81592377620778,
  "U_h": 70.42877127390027,
  "band_width_bp": 385,
  "provenance": {
    "rng_seed": null,
    "params_snapshot": {
      "window": 504,
      "lambda_drift": 0,
      "coverage": 0.95,
      "h": 1,
      "method": "GBM-CC"
    },
    "regime_tag": null,
    "conformal": null
  },
  "locked": true,
  "created_at": "2025-12-22T04:35:26.109Z"
}