{
  "symbol": "AAPL",
  "method": "GBM",
  "date_t": "2023-12-13",
  "created_at": "2025-11-18T15:52:34.262Z",
  "locked": true,
  "target": {
    "h": 1,
    "coverage": 0.95,
    "window_requirements": {
      "min_days": 252
    }
  },
  "estimates": {
    "mu_star_hat": 0.0006822533003388361,
    "sigma_hat": 0.02843401878047764,
    "mu_star_used": 0.00027800658833455856,
    "window_start": "1980-12-15",
    "window_end": "2023-12-13",
    "n": 10839,
    "sigma_forecast": 0.02843401878047764,
    "sigma2_forecast": 0.0008084934240085551,
    "critical_value": 1.96,
    "window_span": {
      "start": "1980-12-15",
      "end": "2023-12-13"
    }
  },
  "intervals": {
    "L_h": 187.2814039834236,
    "U_h": 209.36385545430505,
    "band_width_bp": 1179.1053997457213
  },
  "diagnostics": {
    "method_source": "GBM",
    "m_log": 5.288342996672021,
    "s_scale": 0.02843401878047764
  },
  "provenance": {
    "rng_seed": null,
    "params_snapshot": {
      "mu": 0.0006822533003388361,
      "sigma": 0.02843401878047764,
      "h": 1,
      "coverage": 0.95
    },
    "regime_tag": null,
    "conformal": null
  }
}