{
  "symbol": "AAPL",
  "method": "Range-P",
  "date_t": "2023-11-03",
  "created_at": "2025-11-20T10:32:48.178Z",
  "locked": true,
  "target": {
    "h": 1,
    "coverage": 0.95,
    "window_requirements": {
      "min_days": 22
    }
  },
  "estimates": {
    "mu_star_hat": 0,
    "sigma_hat": 0.17656921380981877,
    "mu_star_used": 0,
    "window_start": "1980-12-15",
    "window_end": "2023-11-03",
    "n": 10812,
    "sigma_forecast": 0.17656921380981877,
    "sigma2_forecast": 0.031176687265417495,
    "critical_value": 1.96,
    "window_span": {
      "start": "1980-12-15",
      "end": "2023-11-03"
    }
  },
  "intervals": {
    "L_h": 124.97262517741234,
    "U_h": 249.69646317104053,
    "band_width_bp": 9980.092665619293
  },
  "diagnostics": {
    "method_source": "Range-P",
    "m_log": 5.174170373805154,
    "s_scale": 0.17656921380981877,
    "range_estimator": "P"
  },
  "provenance": {
    "rng_seed": null,
    "params_snapshot": {
      "estimator": "P",
      "avg_range": 0.031176687265417495,
      "h": 1,
      "coverage": 0.95
    },
    "regime_tag": null,
    "conformal": null
  }
}