{
  "symbol": "AAPL",
  "method": "Range-GK",
  "date_t": "2024-10-21",
  "created_at": "2025-11-21T22:33:53.381Z",
  "locked": true,
  "y_hat": 236.48,
  "target": {
    "h": 1,
    "coverage": 0.95,
    "window_requirements": {
      "min_days": 22
    }
  },
  "estimates": {
    "mu_star_hat": 0,
    "sigma_hat": 0.0223921658974501,
    "mu_star_used": 0,
    "window_start": "1980-12-15",
    "window_end": "2024-10-21",
    "n": 11053,
    "sigma_forecast": 0.0223921658974501,
    "sigma2_forecast": 0.0005014090935789272,
    "critical_value": 1.96,
    "window_span": {
      "start": "1980-12-15",
      "end": "2024-10-21"
    }
  },
  "intervals": {
    "L_h": 226.32567291939174,
    "U_h": 247.08991109425511,
    "band_width_bp": 917.449527798766
  },
  "diagnostics": {
    "method_source": "Range-GK",
    "m_log": 5.465863637759837,
    "s_scale": 0.0223921658974501,
    "range_estimator": "GK"
  },
  "provenance": {
    "rng_seed": null,
    "params_snapshot": {
      "estimator": "GK",
      "avg_range": 0.0005014090935789271,
      "h": 1,
      "coverage": 0.95
    },
    "regime_tag": null,
    "conformal": null
  }
}