{
  "symbol": "AAPL",
  "method": "Range-P",
  "date_t": "2024-12-18",
  "created_at": "2025-11-20T07:58:38.369Z",
  "locked": true,
  "target": {
    "h": 1,
    "coverage": 0.95,
    "window_requirements": {
      "min_days": 22
    }
  },
  "estimates": {
    "mu_star_hat": 0,
    "sigma_hat": 0.17555186420067184,
    "mu_star_used": 0,
    "window_start": "1980-12-15",
    "window_end": "2024-12-18",
    "n": 11094,
    "sigma_forecast": 0.17555186420067184,
    "sigma2_forecast": 0.030818457024331128,
    "critical_value": 1.96,
    "window_span": {
      "start": "1980-12-15",
      "end": "2024-12-18"
    }
  },
  "intervals": {
    "L_h": 175.835462376951,
    "U_h": 349.9226018929921,
    "band_width_bp": 9900.570519889674
  },
  "diagnostics": {
    "method_source": "Range-P",
    "m_log": 5.513630338747058,
    "s_scale": 0.17555186420067184,
    "range_estimator": "P"
  },
  "provenance": {
    "rng_seed": null,
    "params_snapshot": {
      "estimator": "P",
      "avg_range": 0.030818457024331124,
      "h": 1,
      "coverage": 0.95
    },
    "regime_tag": null,
    "conformal": null
  }
}