{
  "symbol": "AAPL",
  "method": "Range-P",
  "date_t": "2024-09-09",
  "created_at": "2025-11-20T10:32:48.392Z",
  "locked": true,
  "target": {
    "h": 1,
    "coverage": 0.95,
    "window_requirements": {
      "min_days": 22
    }
  },
  "estimates": {
    "mu_star_hat": 0,
    "sigma_hat": 0.17582987538531475,
    "mu_star_used": 0,
    "window_start": "1980-12-15",
    "window_end": "2024-09-09",
    "n": 11023,
    "sigma_forecast": 0.17582987538531475,
    "sigma2_forecast": 0.030916145078015312,
    "critical_value": 1.96,
    "window_span": {
      "start": "1980-12-15",
      "end": "2024-09-09"
    }
  },
  "intervals": {
    "L_h": 156.5113956522925,
    "U_h": 311.8062291669632,
    "band_width_bp": 9922.270060109584
  },
  "diagnostics": {
    "method_source": "Range-P",
    "m_log": 5.397755378754093,
    "s_scale": 0.17582987538531475,
    "range_estimator": "P"
  },
  "provenance": {
    "rng_seed": null,
    "params_snapshot": {
      "estimator": "P",
      "avg_range": 0.030916145078015315,
      "h": 1,
      "coverage": 0.95
    },
    "regime_tag": null,
    "conformal": null
  }
}