{
  "symbol": "AAPL",
  "method": "Range-YZ",
  "date_t": "2024-04-12",
  "created_at": "2025-11-20T07:39:16.408Z",
  "locked": true,
  "target": {
    "h": 1,
    "coverage": 0.95,
    "window_requirements": {
      "min_days": 22
    }
  },
  "estimates": {
    "mu_star_hat": 0,
    "sigma_hat": 0.02843683396468842,
    "mu_star_used": 0,
    "window_start": "1980-12-15",
    "window_end": "2024-04-12",
    "n": 10921,
    "sigma_forecast": 0.02843683396468842,
    "sigma2_forecast": 0.0008086535259352569,
    "critical_value": 1.96,
    "window_span": {
      "start": "1980-12-15",
      "end": "2024-04-12"
    }
  },
  "intervals": {
    "L_h": 166.9789785927677,
    "U_h": 186.6696201083963,
    "band_width_bp": 1179.2287676912072
  },
  "diagnostics": {
    "method_source": "Range-YZ",
    "m_log": 5.173604122374395,
    "s_scale": 0.02843683396468842,
    "range_estimator": "YZ"
  },
  "provenance": {
    "rng_seed": null,
    "params_snapshot": {
      "estimator": "YZ",
      "avg_range": 0.000808653525935257,
      "h": 1,
      "coverage": 0.95
    },
    "regime_tag": null,
    "conformal": null
  }
}