{
  "symbol": "AAPL",
  "method": "Range-GK",
  "date_t": "2024-08-02",
  "created_at": "2025-11-21T22:33:53.350Z",
  "locked": true,
  "y_hat": 219.86,
  "target": {
    "h": 1,
    "coverage": 0.95,
    "window_requirements": {
      "min_days": 22
    }
  },
  "estimates": {
    "mu_star_hat": 0,
    "sigma_hat": 0.02242656984972621,
    "mu_star_used": 0,
    "window_start": "1980-12-15",
    "window_end": "2024-08-02",
    "n": 10998,
    "sigma_forecast": 0.02242656984972621,
    "sigma2_forecast": 0.0005029510352246487,
    "critical_value": 1.96,
    "window_span": {
      "start": "1980-12-15",
      "end": "2024-08-02"
    }
  },
  "intervals": {
    "L_h": 210.4051385318571,
    "U_h": 229.73972944430346,
    "band_width_bp": 918.9219924645031
  },
  "diagnostics": {
    "method_source": "Range-GK",
    "m_log": 5.392990980150718,
    "s_scale": 0.02242656984972621,
    "range_estimator": "GK"
  },
  "provenance": {
    "rng_seed": null,
    "params_snapshot": {
      "estimator": "GK",
      "avg_range": 0.0005029510352246487,
      "h": 1,
      "coverage": 0.95
    },
    "regime_tag": null,
    "conformal": null
  }
}