{
  "symbol": "AAPL",
  "method": "GARCH11-t",
  "date_t": "2025-09-26",
  "created_at": "2025-11-20T07:38:09.680Z",
  "locked": true,
  "target": {
    "h": 1,
    "coverage": 0.95,
    "window_requirements": {
      "min_days": 252
    }
  },
  "estimates": {
    "mu_star_hat": 0.0006778256199028139,
    "sigma_hat": 0.028096518677208134,
    "mu_star_used": 0.0006778256199028139,
    "window_start": "1980-12-15",
    "window_end": "2025-09-26",
    "n": 11286,
    "sigma_forecast": 0.028096518677208138,
    "sigma2_forecast": 0.0007894143617787057,
    "critical_value": 2,
    "window_span": {
      "start": "1980-12-15",
      "end": "2025-09-26"
    }
  },
  "intervals": {
    "L_h": 241.66455540183085,
    "U_h": 270.40929121723013,
    "band_width_bp": 1189.4477354200174
  },
  "diagnostics": {
    "method_source": "GARCH11-t",
    "m_log": 5.5437436672345335,
    "s_scale": 0.028096518677208138,
    "garch_params": {
      "omega": 0.00007894143617787056,
      "alpha": 0.1,
      "beta": 0.8
    }
  },
  "provenance": {
    "rng_seed": null,
    "params_snapshot": {
      "omega": 0.00007894143617787056,
      "alpha": 0.1,
      "beta": 0.8,
      "h": 1,
      "coverage": 0.95
    },
    "regime_tag": null,
    "conformal": null
  }
}