{
  "symbol": "AAPL",
  "method": "GARCH11-t",
  "date_t": "2025-08-21",
  "created_at": "2025-11-20T07:38:09.672Z",
  "locked": true,
  "target": {
    "h": 1,
    "coverage": 0.95,
    "window_requirements": {
      "min_days": 252
    }
  },
  "estimates": {
    "mu_star_hat": 0.0006680152875625129,
    "sigma_hat": 0.028116583394152742,
    "mu_star_used": 0.0006680152875625129,
    "window_start": "1980-12-15",
    "window_end": "2025-08-21",
    "n": 11261,
    "sigma_forecast": 0.028116583394152746,
    "sigma2_forecast": 0.0007905422617603459,
    "critical_value": 2,
    "window_span": {
      "start": "1980-12-15",
      "end": "2025-08-21"
    }
  },
  "intervals": {
    "L_h": 212.74424306524105,
    "U_h": 238.06816519365756,
    "band_width_bp": 1190.345823865635
  },
  "diagnostics": {
    "method_source": "GARCH11-t",
    "m_log": 5.416323874252832,
    "s_scale": 0.028116583394152746,
    "garch_params": {
      "omega": 0.00007905422617603459,
      "alpha": 0.1,
      "beta": 0.8
    }
  },
  "provenance": {
    "rng_seed": null,
    "params_snapshot": {
      "omega": 0.00007905422617603459,
      "alpha": 0.1,
      "beta": 0.8,
      "h": 1,
      "coverage": 0.95
    },
    "regime_tag": null,
    "conformal": null
  }
}