{
  "symbol": "AAPL",
  "method": "Range-P",
  "date_t": "2025-08-26",
  "created_at": "2025-11-20T07:58:38.478Z",
  "locked": true,
  "target": {
    "h": 1,
    "coverage": 0.95,
    "window_requirements": {
      "min_days": 22
    }
  },
  "estimates": {
    "mu_star_hat": 0,
    "sigma_hat": 0.17529349093398017,
    "mu_star_used": 0,
    "window_start": "1980-12-15",
    "window_end": "2025-08-26",
    "n": 11264,
    "sigma_forecast": 0.17529349093398017,
    "sigma2_forecast": 0.030727807963821387,
    "critical_value": 1.96,
    "window_span": {
      "start": "1980-12-15",
      "end": "2025-08-26"
    }
  },
  "intervals": {
    "L_h": 162.63355768919865,
    "U_h": 323.32242402572956,
    "band_width_bp": 9880.424963931237
  },
  "diagnostics": {
    "method_source": "Range-P",
    "m_log": 5.435074799902897,
    "s_scale": 0.17529349093398017,
    "range_estimator": "P"
  },
  "provenance": {
    "rng_seed": null,
    "params_snapshot": {
      "estimator": "P",
      "avg_range": 0.030727807963821383,
      "h": 1,
      "coverage": 0.95
    },
    "regime_tag": null,
    "conformal": null
  }
}