{
  "symbol": "AAPL",
  "method": "GBM-CC",
  "date_t": "2022-09-20",
  "created_at": "2025-12-01T10:20:27.769Z",
  "locked": true,
  "y_hat": 156.9841606671093,
  "horizonTrading": 2,
  "target": {
    "h": 2,
    "coverage": 0.95,
    "window_requirements": {
      "min_days": 252
    }
  },
  "estimates": {
    "mu_star_hat": 0.0006802626271587779,
    "sigma_hat": 0.028710141154670275,
    "mu_star_used": 0.000268126524598232,
    "window_start": "1980-12-15",
    "window_end": "2022-09-20",
    "n": 10529,
    "sigma_forecast": 0.04060227099858066,
    "sigma2_forecast": 0.001648544410242184,
    "critical_value": 1.96,
    "window_span": {
      "start": "1980-12-15",
      "end": "2022-09-20"
    }
  },
  "intervals": {
    "L_h": 144.97545636294842,
    "U_h": 169.9875780260354,
    "band_width_bp": 1725.265937461078
  },
  "diagnostics": {
    "method_source": "GBM",
    "m_log": 5.0561449127881835,
    "s_scale": 0.04060227099858066
  },
  "provenance": {
    "rng_seed": null,
    "params_snapshot": {
      "mu": 0.0006802626271587779,
      "sigma": 0.028710141154670275,
      "h": 2,
      "coverage": 0.95
    },
    "regime_tag": null,
    "conformal": null
  }
}