{
  "symbol": "AAPL",
  "method": "Range-YZ",
  "date_t": "2022-04-18",
  "created_at": "2025-12-01T10:21:12.534Z",
  "locked": true,
  "y_hat": 165.07,
  "target": {
    "h": 1,
    "coverage": 0.95,
    "window_requirements": {
      "min_days": 22
    }
  },
  "estimates": {
    "mu_star_hat": 0,
    "sigma_hat": 0.029826575704731174,
    "mu_star_used": 0,
    "window_start": "1980-12-15",
    "window_end": "2022-04-18",
    "n": 10422,
    "sigma_forecast": 0.029826575704731174,
    "sigma2_forecast": 0.0008896246182700599,
    "critical_value": 1.96,
    "window_span": {
      "start": "1980-12-15",
      "end": "2022-04-18"
    }
  },
  "intervals": {
    "L_h": 155.69664612394428,
    "U_h": 175.00765481042413,
    "band_width_bp": 1240.2970241958244
  },
  "diagnostics": {
    "method_source": "Range-YZ",
    "m_log": 5.10636962635945,
    "s_scale": 0.029826575704731174,
    "range_estimator": "YZ"
  },
  "provenance": {
    "rng_seed": null,
    "params_snapshot": {
      "estimator": "YZ",
      "avg_range": 0.0008896246182700598,
      "h": 1,
      "coverage": 0.95
    },
    "regime_tag": null,
    "conformal": null
  }
}