{
  "symbol": "AAPL",
  "method": "Range-YZ",
  "date_t": "2022-09-30",
  "created_at": "2025-12-01T10:21:12.603Z",
  "locked": true,
  "y_hat": 138.2,
  "target": {
    "h": 1,
    "coverage": 0.95,
    "window_requirements": {
      "min_days": 22
    }
  },
  "estimates": {
    "mu_star_hat": 0,
    "sigma_hat": 0.029630475168144602,
    "mu_star_used": 0,
    "window_start": "1980-12-15",
    "window_end": "2022-09-30",
    "n": 10537,
    "sigma_forecast": 0.029630475168144602,
    "sigma2_forecast": 0.0008779650586900339,
    "critical_value": 1.96,
    "window_span": {
      "start": "1980-12-15",
      "end": "2022-09-30"
    }
  },
  "intervals": {
    "L_h": 130.40254680356364,
    "U_h": 146.46370387819806,
    "band_width_bp": 1231.6597695617636
  },
  "diagnostics": {
    "method_source": "Range-YZ",
    "m_log": 4.92870191133357,
    "s_scale": 0.029630475168144602,
    "range_estimator": "YZ"
  },
  "provenance": {
    "rng_seed": null,
    "params_snapshot": {
      "estimator": "YZ",
      "avg_range": 0.0008779650586900339,
      "h": 1,
      "coverage": 0.95
    },
    "regime_tag": null,
    "conformal": null
  }
}