{
  "symbol": "AAPL",
  "method": "GBM-CC",
  "date_t": "2022-09-06",
  "created_at": "2025-12-01T10:20:27.766Z",
  "locked": true,
  "y_hat": 154.61262406231543,
  "horizonTrading": 2,
  "target": {
    "h": 2,
    "coverage": 0.95,
    "window_requirements": {
      "min_days": 252
    }
  },
  "estimates": {
    "mu_star_hat": 0.0006794623056887458,
    "sigma_hat": 0.028712153317365072,
    "mu_star_used": 0.0002672684316288068,
    "window_start": "1980-12-15",
    "window_end": "2022-09-06",
    "n": 10519,
    "sigma_forecast": 0.04060511662635334,
    "sigma2_forecast": 0.0016487754962397564,
    "critical_value": 1.96,
    "window_span": {
      "start": "1980-12-15",
      "end": "2022-09-06"
    }
  },
  "intervals": {
    "L_h": 142.78453711317385,
    "U_h": 167.42053448327698,
    "band_width_bp": 1725.396731900748
  },
  "diagnostics": {
    "method_source": "GBM",
    "m_log": 5.040922789108861,
    "s_scale": 0.04060511662635334
  },
  "provenance": {
    "rng_seed": null,
    "params_snapshot": {
      "mu": 0.0006794623056887458,
      "sigma": 0.028712153317365072,
      "h": 2,
      "coverage": 0.95
    },
    "regime_tag": null,
    "conformal": null
  }
}