{
  "symbol": "AAPL",
  "method": "GBM-CC",
  "date_t": "2023-08-09",
  "created_at": "2025-12-01T10:20:27.836Z",
  "locked": true,
  "y_hat": 178.286639833497,
  "horizonTrading": 2,
  "target": {
    "h": 2,
    "coverage": 0.95,
    "window_requirements": {
      "min_days": 252
    }
  },
  "estimates": {
    "mu_star_hat": 0.000678050853556088,
    "sigma_hat": 0.028529059081397048,
    "mu_star_used": 0.0002710972475211663,
    "window_start": "1980-12-15",
    "window_end": "2023-08-09",
    "n": 10751,
    "sigma_forecast": 0.04034618227465502,
    "sigma2_forecast": 0.0016278144241396871,
    "critical_value": 1.96,
    "window_span": {
      "start": "1980-12-15",
      "end": "2023-08-09"
    }
  },
  "intervals": {
    "L_h": 164.7310384640185,
    "U_h": 192.95772211174398,
    "band_width_bp": 1713.5012266611138
  },
  "diagnostics": {
    "method_source": "GBM",
    "m_log": 5.183392591234366,
    "s_scale": 0.04034618227465502
  },
  "provenance": {
    "rng_seed": null,
    "params_snapshot": {
      "mu": 0.000678050853556088,
      "sigma": 0.028529059081397048,
      "h": 2,
      "coverage": 0.95
    },
    "regime_tag": null,
    "conformal": null
  }
}