{
  "symbol": "AAPL",
  "method": "Range-YZ",
  "date_t": "2023-03-03",
  "created_at": "2025-12-01T10:21:12.668Z",
  "locked": true,
  "y_hat": 151.03,
  "target": {
    "h": 1,
    "coverage": 0.95,
    "window_requirements": {
      "min_days": 22
    }
  },
  "estimates": {
    "mu_star_hat": 0,
    "sigma_hat": 0.029254711170700866,
    "mu_star_used": 0,
    "window_start": "1980-12-15",
    "window_end": "2023-03-03",
    "n": 10642,
    "sigma_forecast": 0.029254711170700866,
    "sigma2_forecast": 0.00085583812568113,
    "critical_value": 1.96,
    "window_span": {
      "start": "1980-12-15",
      "end": "2023-03-03"
    }
  },
  "intervals": {
    "L_h": 142.61365470402964,
    "U_h": 159.94303594097198,
    "band_width_bp": 1215.1277711034413
  },
  "diagnostics": {
    "method_source": "Range-YZ",
    "m_log": 5.01747849257825,
    "s_scale": 0.029254711170700866,
    "range_estimator": "YZ"
  },
  "provenance": {
    "rng_seed": null,
    "params_snapshot": {
      "estimator": "YZ",
      "avg_range": 0.00085583812568113,
      "h": 1,
      "coverage": 0.95
    },
    "regime_tag": null,
    "conformal": null
  }
}