{
  "symbol": "AAPL",
  "method": "GBM-CC",
  "date_t": "2024-01-04",
  "created_at": "2025-12-01T10:20:38.913Z",
  "locked": true,
  "y_hat": 182.0572788757848,
  "horizonTrading": 3,
  "target": {
    "h": 3,
    "coverage": 0.95,
    "window_requirements": {
      "min_days": 252
    }
  },
  "estimates": {
    "mu_star_hat": 0.0006735816751071456,
    "sigma_hat": 0.02841886273350922,
    "mu_star_used": 0.000269765795574126,
    "window_start": "1980-12-15",
    "window_end": "2024-01-04",
    "n": 10853,
    "sigma_forecast": 0.04922291414776372,
    "sigma2_forecast": 0.0024228952771981178,
    "critical_value": 1.96,
    "window_span": {
      "start": "1980-12-15",
      "end": "2024-01-04"
    }
  },
  "intervals": {
    "L_h": 165.31362791096836,
    "U_h": 200.4967963651846,
    "band_width_bp": 2128.267880804391
  },
  "diagnostics": {
    "method_source": "GBM",
    "m_log": 5.204321356660848,
    "s_scale": 0.04922291414776372
  },
  "provenance": {
    "rng_seed": null,
    "params_snapshot": {
      "mu": 0.0006735816751071456,
      "sigma": 0.02841886273350922,
      "h": 3,
      "coverage": 0.95
    },
    "regime_tag": null,
    "conformal": null
  }
}