{
  "symbol": "AAPL",
  "method": "Range-YZ",
  "date_t": "2025-07-14",
  "created_at": "2025-12-01T10:21:02.666Z",
  "locked": true,
  "y_hat": 208.62,
  "target": {
    "h": 1,
    "coverage": 0.95,
    "window_requirements": {
      "min_days": 22
    }
  },
  "estimates": {
    "mu_star_hat": 0,
    "sigma_hat": 0.027532563858807646,
    "mu_star_used": 0,
    "window_start": "1980-12-15",
    "window_end": "2025-07-14",
    "n": 11233,
    "sigma_forecast": 0.027532563858807646,
    "sigma2_forecast": 0.000758042072639321,
    "critical_value": 1.96,
    "window_span": {
      "start": "1980-12-15",
      "end": "2025-07-14"
    }
  },
  "intervals": {
    "L_h": 197.66043626308692,
    "U_h": 220.18723232033966,
    "band_width_bp": 1139.6714731151092
  },
  "diagnostics": {
    "method_source": "Range-YZ",
    "m_log": 5.340514415247825,
    "s_scale": 0.027532563858807646,
    "range_estimator": "YZ"
  },
  "provenance": {
    "rng_seed": null,
    "params_snapshot": {
      "estimator": "YZ",
      "avg_range": 0.0007580420726393209,
      "h": 1,
      "coverage": 0.95
    },
    "regime_tag": null,
    "conformal": null
  }
}