{
  "symbol": "AAPL",
  "method": "Range-YZ",
  "date_t": "2025-06-26",
  "created_at": "2025-12-01T10:21:02.659Z",
  "locked": true,
  "y_hat": 201,
  "target": {
    "h": 1,
    "coverage": 0.95,
    "window_requirements": {
      "min_days": 22
    }
  },
  "estimates": {
    "mu_star_hat": 0,
    "sigma_hat": 0.02760740567932774,
    "mu_star_used": 0,
    "window_start": "1980-12-15",
    "window_end": "2025-06-26",
    "n": 11222,
    "sigma_forecast": 0.02760740567932774,
    "sigma2_forecast": 0.0007621688483429776,
    "critical_value": 1.96,
    "window_span": {
      "start": "1980-12-15",
      "end": "2025-06-26"
    }
  },
  "intervals": {
    "L_h": 190.41280874741165,
    "U_h": 212.175852379727,
    "band_width_bp": 1142.9401086764424
  },
  "diagnostics": {
    "method_source": "Range-YZ",
    "m_log": 5.303304908059076,
    "s_scale": 0.02760740567932774,
    "range_estimator": "YZ"
  },
  "provenance": {
    "rng_seed": null,
    "params_snapshot": {
      "estimator": "YZ",
      "avg_range": 0.0007621688483429777,
      "h": 1,
      "coverage": 0.95
    },
    "regime_tag": null,
    "conformal": null
  }
}