{
  "symbol": "AAPL",
  "method": "GBM-CC",
  "date_t": "2025-09-24",
  "created_at": "2025-12-01T10:20:36.974Z",
  "locked": true,
  "y_hat": 252.52360807977823,
  "horizonTrading": 3,
  "target": {
    "h": 3,
    "coverage": 0.95,
    "window_requirements": {
      "min_days": 252
    }
  },
  "estimates": {
    "mu_star_hat": 0.0006768461197558197,
    "sigma_hat": 0.02809848020907415,
    "mu_star_used": 0.00028208382472595385,
    "window_start": "1980-12-15",
    "window_end": "2025-09-24",
    "n": 11284,
    "sigma_forecast": 0.04866799533758499,
    "sigma2_forecast": 0.002368573770179195,
    "critical_value": 1.96,
    "window_span": {
      "start": "1980-12-15",
      "end": "2025-09-24"
    }
  },
  "intervals": {
    "L_h": 229.54876046400742,
    "U_h": 277.79793935166157,
    "band_width_bp": 2101.9141549762144
  },
  "diagnostics": {
    "method_source": "GBM",
    "m_log": 5.531504741690466,
    "s_scale": 0.04866799533758499
  },
  "provenance": {
    "rng_seed": null,
    "params_snapshot": {
      "mu": 0.0006768461197558197,
      "sigma": 0.02809848020907415,
      "h": 3,
      "coverage": 0.95
    },
    "regime_tag": null,
    "conformal": null
  }
}